poetry_python_downgrader/__init__.py
poetry_python_downgrader/cli.py
poetry_python_downgrader/downgrader.py
poetry_python_downgrader/gh_actions_cli.py
poetry_python_downgrader/py.typed
poetry_python_downgrader/pypi.py
poetry_python_downgrader/read_toml.py
poetry_python_downgrader-0.1.6.dist-info/LICENSE
poetry_python_downgrader-0.1.6.dist-info/METADATA
poetry_python_downgrader-0.1.6.dist-info/WHEEL
poetry_python_downgrader-0.1.6.dist-info/entry_points.txt
poetry_python_downgrader-0.1.6.dist-info/RECORD
