Metadata-Version: 2.1
Name: poetry-python-downgrader
Version: 0.1.6
Summary: A tool to downgrade poetry packages for compatibility with specific Python versions.
Home-page: https://github.com/rizerphe/poetry-python-downgrader
License: MIT
Author: rizerphe
Author-email: 44440399+rizerphe@users.noreply.github.com
Requires-Python: >=3.8,<4.0
Classifier: License :: OSI Approved :: MIT License
Classifier: Programming Language :: Python :: 3
Classifier: Programming Language :: Python :: 3.8
Classifier: Programming Language :: Python :: 3.9
Classifier: Programming Language :: Python :: 3.10
Classifier: Programming Language :: Python :: 3.11
Classifier: Programming Language :: Python :: 3.12
Requires-Dist: aiohttp (>=3.9.5,<4.0.0)
Requires-Dist: click (>=8.1.7,<9.0.0)
Requires-Dist: poetry-core (>=1.9.0,<2.0.0)
Requires-Dist: pytest-cov (>=5.0.0,<6.0.0)
Requires-Dist: toml (>=0.10.2,<0.11.0)
